pyreptasks/__init__.py
pyreptasks/data_formatter.py
pyreptasks/switch.py
pyreptasks-3.1.0.dist-info/LICENSE.txt
pyreptasks-3.1.0.dist-info/METADATA
pyreptasks-3.1.0.dist-info/WHEEL
pyreptasks-3.1.0.dist-info/top_level.txt
pyreptasks-3.1.0.dist-info/RECORD
