Metadata-Version: 2.1
Name: pyreptasks
Version: 3.1.0
Summary: This Python library provides the user with some tools useful to automate coding of repetitive tasks
Home-page: https://github.com/tsenovilla/pyreptasks
Author: Tomás Senovilla Polo
Author-email: Tomas Senovilla Polo <tspscgs@gmail.com>
License: MIT License
Classifier: Programming Language :: Python :: 3
Classifier: License :: OSI Approved :: MIT License
Classifier: Operating System :: OS Independent
Requires-Python: >=3.7
License-File: LICENSE.txt
